chabotmat/__init__.py
chabotmat/main.py
chabotmat-0.1.dist-info/METADATA
chabotmat-0.1.dist-info/WHEEL
chabotmat-0.1.dist-info/top_level.txt
chabotmat-0.1.dist-info/RECORD
