Metadata-Version: 2.2
Name: chabotmat
Version: 0.1
Requires-Dist: numpy
Requires-Dist: random
Dynamic: requires-dist
